pint_pandas/__init__.py
pint_pandas/pint_array.py
pint_pandas/py.typed
pint_pandas/testsuite/__init__.py
pint_pandas/testsuite/pandas_test.csv
pint_pandas/testsuite/test_issues.py
pint_pandas/testsuite/test_pandas_extensiontests.py
pint_pandas/testsuite/test_pandas_interface.py
Pint_Pandas-0.7.dist-info/AUTHORS
Pint_Pandas-0.7.dist-info/LICENSE
Pint_Pandas-0.7.dist-info/METADATA
Pint_Pandas-0.7.dist-info/WHEEL
Pint_Pandas-0.7.dist-info/top_level.txt
Pint_Pandas-0.7.dist-info/RECORD
