Metadata-Version: 2.1
Name: Pint-Pandas
Version: 0.7
Summary: Extend Pandas Dataframe with Physical quantities module
Author-email: "Hernan E. Grecco" <hernan.grecco@gmail.com>
License: BSD
Project-URL: Homepage, https://github.com/hgrecco/pint-pandas
Keywords: physical,quantities,unit,conversion,science,pandas,dataframe
Classifier: Development Status :: 4 - Beta
Classifier: Intended Audience :: Developers
Classifier: Intended Audience :: Science/Research
Classifier: License :: OSI Approved :: BSD License
Classifier: Operating System :: MacOS :: MacOS X
Classifier: Operating System :: Microsoft :: Windows
Classifier: Operating System :: POSIX
Classifier: Programming Language :: Python
Classifier: Topic :: Scientific/Engineering
Classifier: Topic :: Software Development :: Libraries
Classifier: Programming Language :: Python :: 3.9
Classifier: Programming Language :: Python :: 3.10
Classifier: Programming Language :: Python :: 3.11
Requires-Python: >=3.9
License-File: LICENSE
License-File: AUTHORS
Requires-Dist: pint>=0.24
Requires-Dist: pandas>=2.2
Provides-Extra: test
Requires-Dist: pytest; extra == "test"
Requires-Dist: pytest-mpl; extra == "test"
Requires-Dist: pytest-cov; extra == "test"
Requires-Dist: pytest-subtests; extra == "test"
Requires-Dist: codecov; extra == "test"
Requires-Dist: coveralls; extra == "test"
Requires-Dist: nbval; extra == "test"
Requires-Dist: pyarrow; extra == "test"
